connectors/__init__.py
connectors/airtable/__init__.py
connectors/airtable/methods.py
connectors/airtable/methods_test.py
connectors/bb/__init__.py
connectors/bb/generate.py
connectors/generators/__init__.py
connectors/generators/openapi.py
connectors/google_sheets/__init__.py
connectors/google_sheets/entities.py
connectors/itau/__init__.py
connectors/itau/generate.py
connectors/itau/sandbox_test.py
connectors/itau/utils/__init__.py
connectors/itau/utils/auth.py
connectors/itau/utils/currency.py
connectors/monday/__init__.py
connectors/monday/monday.py
connectors/monday/monday_test.py
connectors/slack/__init__.py
connectors/slack/methods.py
connectors/utils/__init__.py
connectors/utils/json_schema.py
connectors/utils/string.py
connectors/utils/string_test.py
abstra_connectors-0.0.8.dist-info/METADATA
abstra_connectors-0.0.8.dist-info/WHEEL
abstra_connectors-0.0.8.dist-info/top_level.txt
abstra_connectors-0.0.8.dist-info/RECORD
