Metadata-Version: 2.1
Name: abstra-connectors
Version: 0.0.8
Summary: Abstra Connectors
Home-page: https://github.com/abstra-app/connectors
License: MIT
Platform: UNKNOWN
Requires-Python: >=3.8, <4
Requires-Dist: gql
Requires-Dist: aiohttp
Requires-Dist: pydantic
